{
  "generated_at": "2026-06-16",
  "excel_date": "20260616",
  "underlying_close": 69404.5,
  "months": {
    "202604": {
      "max_pain": 52824.0,
      "pcr": null,
      "oi_by_strike": {
        "30166.0": {
          "call_oi": 0.0,
          "put_oi": 425935.0
        },
        "16347.0": {
          "call_oi": 0.0,
          "put_oi": 217190.0
        },
        "46513.0": {
          "call_oi": 0.0,
          "put_oi": 643125.0
        },
        "39581.0": {
          "call_oi": 0.0,
          "put_oi": 65874.0
        },
        "13243.0": {
          "call_oi": 0.0,
          "put_oi": 31335.0
        },
        "52824.0": {
          "call_oi": 0.0,
          "put_oi": 97209.0
        }
      }
    }
  }
}